<?xml version="1.0" encoding="UTF-8"?>
<PMML version="3.0"><Header copyright="Copyright 1984-2017 TIBCO Software Inc. All rights reserved."><Application name="STATISTICA Automated Neural Networks (SANN)" version="2.0"/></Header><DataDictionary numberOfFields="23"><DataField name="E-cadherin" optype="categorical"><Value value="0"/><Value value="1"/></DataField><DataField name="wavelet-LLLglrlmShortRunEmphasis" optype="continuous"/><DataField name="wavelet-LLLglcmImc2" optype="continuous"/><DataField name="wavelet-LLHglcmImc2" optype="continuous"/><DataField name="wavelet-HLHglcmIdmn" optype="continuous"/><DataField name="wavelet-LLLglcmIdmn" optype="continuous"/><DataField name="wavelet-HHLglcmIdmn" optype="continuous"/><DataField name="wavelet-LHHglcmIdmn" optype="continuous"/><DataField name="wavelet-LHHglrlmShortRunEmphasis" optype="continuous"/><DataField name="wavelet-LHLglrlmShortRunEmphasis" optype="continuous"/><DataField name="wavelet-LLHglcmIdmn" optype="continuous"/><DataField name="wavelet-HHLglcmIdn" optype="continuous"/><DataField name="wavelet-HHHglcmIdn" optype="continuous"/><DataField name="wavelet-HLLglrlmShortRunEmphasis" optype="continuous"/><DataField name="wavelet-HLHglrlmShortRunEmphasis" optype="continuous"/><DataField name="wavelet-LLHglrlmLongRunEmphasis" optype="continuous"/><DataField name="wavelet-LLLglcmMCC" optype="continuous"/><DataField name="wavelet-HHHglrlmShortRunEmphasis" optype="continuous"/><DataField name="wavelet-HHLglrlmShortRunEmphasis" optype="continuous"/><DataField name="wavelet-LLHglcmMCC" optype="continuous"/><DataField name="wavelet-LHLglrlmRunEntropy" optype="continuous"/><DataField name="wavelet-LHHglszmSmallAreaEmphasis" optype="continuous"/><DataField name="wavelet-LHLgldmDependenceEntropy" optype="continuous"/></DataDictionary><NeuralNetwork modelName="AllC_RBF 22-28-2" functionName="classification"><MiningSchema><MiningField name="E-cadherin" usageType="predicted"/><MiningField name="wavelet-LLLglrlmShortRunEmphasis" lowValue="0.944652" highValue="1.000000"/><MiningField name="wavelet-LLLglcmImc2" lowValue="0.957135" highValue="0.999976"/><MiningField name="wavelet-LLHglcmImc2" lowValue="0.926863" highValue="0.999980"/><MiningField name="wavelet-HLHglcmIdmn" lowValue="0.863418" highValue="0.995831"/><MiningField name="wavelet-LLLglcmIdmn" lowValue="0.820202" highValue="0.994174"/><MiningField name="wavelet-HHLglcmIdmn" lowValue="0.882155" highValue="0.997911"/><MiningField name="wavelet-LHHglcmIdmn" lowValue="0.845091" highValue="0.995171"/><MiningField name="wavelet-LHHglrlmShortRunEmphasis" lowValue="0.782159" highValue="0.991759"/><MiningField name="wavelet-LHLglrlmShortRunEmphasis" lowValue="0.792043" highValue="1.000000"/><MiningField name="wavelet-LLHglcmIdmn" lowValue="0.787738" highValue="0.986949"/><MiningField name="wavelet-HHLglcmIdn" lowValue="0.763911" highValue="0.976060"/><MiningField name="wavelet-HHHglcmIdn" lowValue="0.764171" highValue="0.978344"/><MiningField name="wavelet-HLLglrlmShortRunEmphasis" lowValue="0.697980" highValue="0.993238"/><MiningField name="wavelet-HLHglrlmShortRunEmphasis" lowValue="0.476397" highValue="0.998521"/><MiningField name="wavelet-LLHglrlmLongRunEmphasis" lowValue="1.009666" highValue="1.912738"/><MiningField name="wavelet-LLLglcmMCC" lowValue="0.635162" highValue="1.000000"/><MiningField name="wavelet-HHHglrlmShortRunEmphasis" lowValue="0.462825" highValue="0.998521"/><MiningField name="wavelet-HHLglrlmShortRunEmphasis" lowValue="0.602714" highValue="1.000000"/><MiningField name="wavelet-LLHglcmMCC" lowValue="0.617261" highValue="1.000000"/><MiningField name="wavelet-LHLglrlmRunEntropy" lowValue="2.517844" highValue="5.108904"/><MiningField name="wavelet-LHHglszmSmallAreaEmphasis" lowValue="0.157424" highValue="0.953722"/><MiningField name="wavelet-LHLgldmDependenceEntropy" lowValue="3.135883" highValue="6.871797"/></MiningSchema><NeuralInputs numberOfInputs="22"><NeuralInput id="0"><DerivedField><NormContinuous field="wavelet-LLLglrlmShortRunEmphasis" shift="-1.70674284402184e+001" scale="1.80674284402184e+001"><LinearNorm orig="9.44651780229333e-001" norm="0.000000"/><LinearNorm orig="1.00000000000000e+000" norm="1.000000"/></NormContinuous></DerivedField></NeuralInput><NeuralInput id="1"><DerivedField><NormContinuous field="wavelet-LLLglcmImc2" shift="-2.23414473483306e+001" scale="2.33420074663241e+001"><LinearNorm orig="9.57134787167000e-001" norm="0.000000"/><LinearNorm orig="9.99976003863667e-001" norm="1.000000"/></NormContinuous></DerivedField></NeuralInput><NeuralInput id="2"><DerivedField><NormContinuous field="wavelet-LLHglcmImc2" shift="-1.26764896657576e+001" scale="1.36767659612488e+001"><LinearNorm orig="9.26863097729000e-001" norm="0.000000"/><LinearNorm orig="9.99979798185333e-001" norm="1.000000"/></NormContinuous></DerivedField></NeuralInput><NeuralInput id="3"><DerivedField><NormContinuous field="wavelet-HLHglcmIdmn" shift="-6.52064315436853e+000" scale="7.55212528163418e+000"><LinearNorm orig="8.63418297658000e-001" norm="0.000000"/><LinearNorm orig="9.95831355268667e-001" norm="1.000000"/></NormContinuous></DerivedField></NeuralInput><NeuralInput id="4"><DerivedField><NormContinuous field="wavelet-LLLglcmIdmn" shift="-4.71457306025223e+000" scale="5.74806361639079e+000"><LinearNorm orig="8.20201962763333e-001" norm="0.000000"/><LinearNorm orig="9.94173593339667e-001" norm="1.000000"/></NormContinuous></DerivedField></NeuralInput><NeuralInput id="5"><DerivedField><NormContinuous field="wavelet-HHLglcmIdmn" shift="-7.62084107610030e+000" scale="8.63888738876681e+000"><LinearNorm orig="8.82155390289000e-001" norm="0.000000"/><LinearNorm orig="9.97911037399333e-001" norm="1.000000"/></NormContinuous></DerivedField></NeuralInput><NeuralInput id="6"><DerivedField><NormContinuous field="wavelet-LHHglcmIdmn" shift="-5.63095904599203e+000" scale="6.66313735509937e+000"><LinearNorm orig="8.45091245445000e-001" norm="0.000000"/><LinearNorm orig="9.95170697016667e-001" norm="1.000000"/></NormContinuous></DerivedField></NeuralInput><NeuralInput id="7"><DerivedField><NormContinuous field="wavelet-LHHglrlmShortRunEmphasis" shift="-3.73167170151854e+000" scale="4.77098935728974e+000"><LinearNorm orig="7.82158881955333e-001" norm="0.000000"/><LinearNorm orig="9.91759014152667e-001" norm="1.000000"/></NormContinuous></DerivedField></NeuralInput><NeuralInput id="8"><DerivedField><NormContinuous field="wavelet-LHLglrlmShortRunEmphasis" shift="-3.80868230647489e+000" scale="4.80868230647489e+000"><LinearNorm orig="7.92042822489333e-001" norm="0.000000"/><LinearNorm orig="1.00000000000000e+000" norm="1.000000"/></NormContinuous></DerivedField></NeuralInput><NeuralInput id="9"><DerivedField><NormContinuous field="wavelet-LLHglcmIdmn" shift="-3.95429425267832e+000" scale="5.01980730472617e+000"><LinearNorm orig="7.87738256198667e-001" norm="0.000000"/><LinearNorm orig="9.86949090259667e-001" norm="1.000000"/></NormContinuous></DerivedField></NeuralInput><NeuralInput id="10"><DerivedField><NormContinuous field="wavelet-HHLglcmIdn" shift="-3.60081013653434e+000" scale="4.71365444382257e+000"><LinearNorm orig="7.63910502869667e-001" norm="0.000000"/><LinearNorm orig="9.76060123067333e-001" norm="1.000000"/></NormContinuous></DerivedField></NeuralInput><NeuralInput id="11"><DerivedField><NormContinuous field="wavelet-HHHglcmIdn" shift="-3.56800859016376e+000" scale="4.66912393132811e+000"><LinearNorm orig="7.64170890008667e-001" norm="0.000000"/><LinearNorm orig="9.78343830095000e-001" norm="1.000000"/></NormContinuous></DerivedField></NeuralInput><NeuralInput id="12"><DerivedField><NormContinuous field="wavelet-HLLglrlmShortRunEmphasis" shift="-2.36396389055986e+000" scale="3.38686484068959e+000"><LinearNorm orig="6.97979990863333e-001" norm="0.000000"/><LinearNorm orig="9.93238304093333e-001" norm="1.000000"/></NormContinuous></DerivedField></NeuralInput><NeuralInput id="13"><DerivedField><NormContinuous field="wavelet-HLHglrlmShortRunEmphasis" shift="-9.12420415187473e-001" scale="1.91525363061707e+000"><LinearNorm orig="4.76396650867333e-001" norm="0.000000"/><LinearNorm orig="9.98520710059333e-001" norm="1.000000"/></NormContinuous></DerivedField></NeuralInput><NeuralInput id="14"><DerivedField><NormContinuous field="wavelet-LLHglrlmLongRunEmphasis" shift="-1.11803506920969e+000" scale="1.10733165333808e+000"><LinearNorm orig="1.00966595314000e+000" norm="0.000000"/><LinearNorm orig="1.91273776273333e+000" norm="1.000000"/></NormContinuous></DerivedField></NeuralInput><NeuralInput id="15"><DerivedField><NormContinuous field="wavelet-LLLglcmMCC" shift="-1.74094446902662e+000" scale="2.74094446902662e+000"><LinearNorm orig="6.35162254726333e-001" norm="0.000000"/><LinearNorm orig="1.00000000000000e+000" norm="1.000000"/></NormContinuous></DerivedField></NeuralInput><NeuralInput id="16"><DerivedField><NormContinuous field="wavelet-HHHglrlmShortRunEmphasis" shift="-8.63971690126955e-001" scale="1.86673312966758e+000"><LinearNorm orig="4.62825497869000e-001" norm="0.000000"/><LinearNorm orig="9.98520710059333e-001" norm="1.000000"/></NormContinuous></DerivedField></NeuralInput><NeuralInput id="17"><DerivedField><NormContinuous field="wavelet-HHLglrlmShortRunEmphasis" shift="-1.51707556409883e+000" scale="2.51707556409883e+000"><LinearNorm orig="6.02713556055667e-001" norm="0.000000"/><LinearNorm orig="1.00000000000000e+000" norm="1.000000"/></NormContinuous></DerivedField></NeuralInput><NeuralInput id="18"><DerivedField><NormContinuous field="wavelet-LLHglcmMCC" shift="-1.61274735192019e+000" scale="2.61274735192019e+000"><LinearNorm orig="6.17261118161667e-001" norm="0.000000"/><LinearNorm orig="1.00000000000000e+000" norm="1.000000"/></NormContinuous></DerivedField></NeuralInput><NeuralInput id="19"><DerivedField><NormContinuous field="wavelet-LHLglrlmRunEntropy" shift="-9.71743008586418e-001" scale="3.85942444610278e-001"><LinearNorm orig="2.51784436295333e+000" norm="0.000000"/><LinearNorm orig="5.10890428384333e+000" norm="1.000000"/></NormContinuous></DerivedField></NeuralInput><NeuralInput id="20"><DerivedField><NormContinuous field="wavelet-LHHglszmSmallAreaEmphasis" shift="-1.97694436648700e-001" scale="1.25581026244704e+000"><LinearNorm orig="1.57423810395910e-001" norm="0.000000"/><LinearNorm orig="9.53722447143333e-001" norm="1.000000"/></NormContinuous></DerivedField></NeuralInput><NeuralInput id="21"><DerivedField><NormContinuous field="wavelet-LHLgldmDependenceEntropy" shift="-8.39388553160572e-001" scale="2.67672126578350e-001"><LinearNorm orig="3.13588330578333e+000" norm="0.000000"/><LinearNorm orig="6.87179713731667e+000" norm="1.000000"/></NormContinuous></DerivedField></NeuralInput></NeuralInputs><NeuralLayer numberOfNeurons="28" activationFunction="radialBasis"><Neuron id="22" width="3.88073603211138e-001"><Con from="0" weight="7.21274688395500e-001"/><Con from="1" weight="9.80034929398578e-001"/><Con from="2" weight="9.97586739446685e-001"/><Con from="3" weight="7.78132608774025e-001"/><Con from="4" weight="9.23321307061344e-001"/><Con from="5" weight="8.50861741608640e-001"/><Con from="6" weight="8.77262193328730e-001"/><Con from="7" weight="8.39599375439893e-001"/><Con from="8" weight="7.41987311835320e-001"/><Con from="9" weight="6.42553057924906e-001"/><Con from="10" weight="7.35657400741915e-001"/><Con from="11" weight="7.50513021407866e-001"/><Con from="12" weight="5.98045698179714e-001"/><Con from="13" weight="8.54140715046686e-001"/><Con from="14" weight="5.45166479678991e-002"/><Con from="15" weight="8.00058514053649e-001"/><Con from="16" weight="6.90976474091548e-001"/><Con from="17" weight="3.97792992685509e-001"/><Con from="18" weight="8.79831929068478e-001"/><Con from="19" weight="6.77252503471210e-001"/><Con from="20" weight="7.17957527990548e-001"/><Con from="21" weight="7.51783400245235e-001"/></Neuron><Neuron id="23" width="5.10616124821454e-001"><Con from="0" weight="6.75115237812999e-001"/><Con from="1" weight="8.92600661533237e-001"/><Con from="2" weight="9.54805681587887e-001"/><Con from="3" weight="8.66972582856654e-001"/><Con from="4" weight="8.24696960554430e-001"/><Con from="5" weight="7.55117283807491e-001"/><Con from="6" weight="8.75508067475769e-001"/><Con from="7" weight="7.36846674205637e-001"/><Con from="8" weight="7.75742976764493e-001"/><Con from="9" weight="8.64517006268500e-001"/><Con from="10" weight="6.47464962735660e-001"/><Con from="11" weight="6.96964296436463e-001"/><Con from="12" weight="7.54172269251367e-001"/><Con from="13" weight="8.60333082817168e-001"/><Con from="14" weight="5.76375628978010e-002"/><Con from="15" weight="4.85396496327876e-001"/><Con from="16" weight="6.74113376645276e-001"/><Con from="17" weight="5.82272183628998e-001"/><Con from="18" weight="7.89626582647513e-001"/><Con from="19" weight="4.54480832979802e-001"/><Con from="20" weight="5.70739931315382e-001"/><Con from="21" weight="6.45018878326477e-001"/></Neuron><Neuron id="24" width="3.55794735090750e-001"><Con from="0" weight="8.96725689088388e-001"/><Con from="1" weight="9.98726869016828e-001"/><Con from="2" weight="9.97591294972274e-001"/><Con from="3" weight="5.70895837787656e-001"/><Con from="4" weight="8.77104267332720e-001"/><Con from="5" weight="7.83481119242697e-001"/><Con from="6" weight="7.07453398750588e-001"/><Con from="7" weight="8.41159416731718e-001"/><Con from="8" weight="6.98112337904536e-001"/><Con from="9" weight="4.45084234582927e-001"/><Con from="10" weight="6.39809598325926e-001"/><Con from="11" weight="5.36881307171590e-001"/><Con from="12" weight="8.81750668070766e-001"/><Con from="13" weight="9.47316126703868e-001"/><Con from="14" weight="4.17404564246568e-002"/><Con from="15" weight="9.94358988451731e-001"/><Con from="16" weight="8.11184336944577e-001"/><Con from="17" weight="7.09153630658847e-001"/><Con from="18" weight="9.74838520606848e-001"/><Con from="19" weight="4.14700408812204e-001"/><Con from="20" weight="6.51562552338840e-001"/><Con from="21" weight="5.80067241833010e-001"/></Neuron><Neuron id="25" width="3.74533566457626e-001"><Con from="0" weight="8.68244682511033e-001"/><Con from="1" weight="9.98931681080460e-001"/><Con from="2" weight="9.99235951230688e-001"/><Con from="3" weight="6.27988943319803e-001"/><Con from="4" weight="8.66239988010824e-001"/><Con from="5" weight="7.49772275541267e-001"/><Con from="6" weight="6.29265667509246e-001"/><Con from="7" weight="9.34996578966026e-001"/><Con from="8" weight="8.66764334042223e-001"/><Con from="9" weight="5.24508700448850e-001"/><Con from="10" weight="6.24286294249625e-001"/><Con from="11" weight="4.67542808098456e-001"/><Con from="12" weight="8.47090012077558e-001"/><Con from="13" weight="9.31595525034279e-001"/><Con from="14" weight="1.44434000649485e-002"/><Con from="15" weight="9.86319605566242e-001"/><Con from="16" weight="8.31072431943171e-001"/><Con from="17" weight="6.05291624981029e-001"/><Con from="18" weight="9.83201040044713e-001"/><Con from="19" weight="6.67623350349156e-001"/><Con from="20" weight="7.89859571986504e-001"/><Con from="21" weight="6.15725527150579e-001"/></Neuron><Neuron id="26" width="5.02396242130383e-001"><Con from="0" weight="8.01049523791505e-001"/><Con from="1" weight="9.75839974970945e-001"/><Con from="2" weight="9.81729070759545e-001"/><Con from="3" weight="9.29692737798516e-001"/><Con from="4" weight="8.78527110353236e-001"/><Con from="5" weight="9.67531686025787e-001"/><Con from="6" weight="9.50908247357132e-001"/><Con from="7" weight="8.74560959085751e-001"/><Con from="8" weight="8.06924411498418e-001"/><Con from="9" weight="8.85924338519119e-001"/><Con from="10" weight="9.12306498449856e-001"/><Con from="11" weight="8.48865644746630e-001"/><Con from="12" weight="7.44274321804278e-001"/><Con from="13" weight="8.81827875212614e-001"/><Con from="14" weight="5.19509189320468e-002"/><Con from="15" weight="6.33744359317588e-001"/><Con from="16" weight="7.26795036025075e-001"/><Con from="17" weight="5.13771061697573e-001"/><Con from="18" weight="4.82238177248900e-001"/><Con from="19" weight="9.19325571311039e-001"/><Con from="20" weight="7.84622143787830e-001"/><Con from="21" weight="9.25770239536588e-001"/></Neuron><Neuron id="27" width="1.18847944106535e+000"><Con from="0" weight="5.33943338860478e-001"/><Con from="1" weight="7.01000818230032e-001"/><Con from="2" weight="0.00000000000000e+000"/><Con from="3" weight="9.70641624566236e-001"/><Con from="4" weight="9.67110566021341e-001"/><Con from="5" weight="9.31173728592213e-001"/><Con from="6" weight="9.08261402405074e-001"/><Con from="7" weight="5.89075901878515e-001"/><Con from="8" weight="5.22965677685037e-001"/><Con from="9" weight="9.49866401973523e-001"/><Con from="10" weight="8.42419108191105e-001"/><Con from="11" weight="8.76889785723141e-001"/><Con from="12" weight="4.73463000102230e-001"/><Con from="13" weight="7.60757904347534e-001"/><Con from="14" weight="1.22770117982009e-001"/><Con from="15" weight="5.71174711574928e-001"/><Con from="16" weight="4.94775648423805e-001"/><Con from="17" weight="1.90388291059498e-001"/><Con from="18" weight="9.42815453537038e-002"/><Con from="19" weight="4.71481190913710e-001"/><Con from="20" weight="6.19990667825734e-001"/><Con from="21" weight="7.58062254291245e-001"/></Neuron><Neuron id="28" width="4.19246269211276e-001"><Con from="0" weight="6.86370520534794e-001"/><Con from="1" weight="9.51058743915265e-001"/><Con from="2" weight="9.86294488494709e-001"/><Con from="3" weight="6.39587021457853e-001"/><Con from="4" weight="8.89043412721649e-001"/><Con from="5" weight="7.84603999922054e-001"/><Con from="6" weight="6.60988562105912e-001"/><Con from="7" weight="8.38868528259308e-001"/><Con from="8" weight="7.40814863929208e-001"/><Con from="9" weight="5.73347156181069e-001"/><Con from="10" weight="6.59737333280439e-001"/><Con from="11" weight="5.79001917260631e-001"/><Con from="12" weight="7.56777791163973e-001"/><Con from="13" weight="8.56499386062995e-001"/><Con from="14" weight="5.79972346203403e-002"/><Con from="15" weight="9.38987929430649e-001"/><Con from="16" weight="6.46012386353086e-001"/><Con from="17" weight="4.72012811281010e-001"/><Con from="18" weight="7.13298417068019e-001"/><Con from="19" weight="5.57338976746101e-001"/><Con from="20" weight="6.51172729359108e-001"/><Con from="21" weight="6.89610304556355e-001"/></Neuron><Neuron id="29" width="4.64422499148223e-001"><Con from="0" weight="8.77923469595537e-001"/><Con from="1" weight="9.97971057592771e-001"/><Con from="2" weight="9.98826274077866e-001"/><Con from="3" weight="8.23228257257758e-001"/><Con from="4" weight="7.44915741723792e-001"/><Con from="5" weight="8.63100688905811e-001"/><Con from="6" weight="6.86392746747712e-001"/><Con from="7" weight="6.90572921498575e-001"/><Con from="8" weight="7.06421556552421e-001"/><Con from="9" weight="5.86414896656149e-001"/><Con from="10" weight="7.50311977856422e-001"/><Con from="11" weight="5.57751913863849e-001"/><Con from="12" weight="8.40998605753860e-001"/><Con from="13" weight="9.37043759045436e-001"/><Con from="14" weight="2.50524415589071e-002"/><Con from="15" weight="9.59365421601650e-001"/><Con from="16" weight="5.70914084929951e-001"/><Con from="17" weight="4.49134205252844e-001"/><Con from="18" weight="8.90850422219068e-001"/><Con from="19" weight="5.50804310210543e-001"/><Con from="20" weight="4.76471404320348e-001"/><Con from="21" weight="6.90631781548442e-001"/></Neuron><Neuron id="30" width="3.20669304701022e-001"><Con from="0" weight="7.98799371726702e-001"/><Con from="1" weight="9.94182388762876e-001"/><Con from="2" weight="9.99420933269658e-001"/><Con from="3" weight="7.11244751691418e-001"/><Con from="4" weight="7.41207426447352e-001"/><Con from="5" weight="7.82508007426453e-001"/><Con from="6" weight="7.47052421313393e-001"/><Con from="7" weight="8.85810789620750e-001"/><Con from="8" weight="8.08382755304085e-001"/><Con from="9" weight="7.17535450780571e-001"/><Con from="10" weight="6.34581640890508e-001"/><Con from="11" weight="5.07157736130820e-001"/><Con from="12" weight="9.11197508986280e-001"/><Con from="13" weight="9.58493034231103e-001"/><Con from="14" weight="2.08762184502502e-002"/><Con from="15" weight="9.64805944189331e-001"/><Con from="16" weight="8.89240368685769e-001"/><Con from="17" weight="7.58142504201670e-001"/><Con from="18" weight="9.87821359237718e-001"/><Con from="19" weight="5.53901836739600e-001"/><Con from="20" weight="7.56326023877715e-001"/><Con from="21" weight="5.32089266783436e-001"/></Neuron><Neuron id="31" width="5.02396242130383e-001"><Con from="0" weight="7.32483353375827e-001"/><Con from="1" weight="8.94380246137626e-001"/><Con from="2" weight="9.24745726908824e-001"/><Con from="3" weight="9.05379062190585e-001"/><Con from="4" weight="9.03969575035572e-001"/><Con from="5" weight="8.14773139307580e-001"/><Con from="6" weight="8.01001999570395e-001"/><Con from="7" weight="7.81196354392136e-001"/><Con from="8" weight="6.77826489839572e-001"/><Con from="9" weight="8.83664945897286e-001"/><Con from="10" weight="7.30616452854900e-001"/><Con from="11" weight="7.13337991415170e-001"/><Con from="12" weight="7.24821850651695e-001"/><Con from="13" weight="8.32439638557570e-001"/><Con from="14" weight="6.68103149041597e-002"/><Con from="15" weight="5.24898592127173e-001"/><Con from="16" weight="6.33106388465970e-001"/><Con from="17" weight="4.21243413251512e-001"/><Con from="18" weight="4.72730813189478e-001"/><Con from="19" weight="6.86157155799258e-001"/><Con from="20" weight="6.42872484580763e-001"/><Con from="21" weight="8.40744324020144e-001"/></Neuron><Neuron id="32" width="4.13777156445039e-001"><Con from="0" weight="7.77357804911173e-001"/><Con from="1" weight="9.84019815243641e-001"/><Con from="2" weight="9.84893322741504e-001"/><Con from="3" weight="8.45146828276135e-001"/><Con from="4" weight="8.07224066995501e-001"/><Con from="5" weight="8.61832094638497e-001"/><Con from="6" weight="8.91507379836795e-001"/><Con from="7" weight="5.60303882391799e-001"/><Con from="8" weight="5.37256080325813e-001"/><Con from="9" weight="6.93824733796071e-001"/><Con from="10" weight="7.57065853518946e-001"/><Con from="11" weight="8.69027761754778e-001"/><Con from="12" weight="8.22263835317921e-001"/><Con from="13" weight="9.08346791068412e-001"/><Con from="14" weight="5.34021213459392e-002"/><Con from="15" weight="8.30535738534153e-001"/><Con from="16" weight="5.88329070342748e-001"/><Con from="17" weight="3.67228888188398e-001"/><Con from="18" weight="6.82227678859030e-001"/><Con from="19" weight="4.77032414362475e-001"/><Con from="20" weight="4.93926015757466e-001"/><Con from="21" weight="7.41895337751699e-001"/></Neuron><Neuron id="33" width="4.05356991983678e-001"><Con from="0" weight="7.75162413626020e-001"/><Con from="1" weight="9.90087277235691e-001"/><Con from="2" weight="9.97692046044930e-001"/><Con from="3" weight="6.97561086452041e-001"/><Con from="4" weight="8.72296879831881e-001"/><Con from="5" weight="8.42284843587238e-001"/><Con from="6" weight="7.97846486720097e-001"/><Con from="7" weight="7.55513515738523e-001"/><Con from="8" weight="7.16084440900636e-001"/><Con from="9" weight="3.76121636942312e-001"/><Con from="10" weight="7.41239842538873e-001"/><Con from="11" weight="7.34239908801164e-001"/><Con from="12" weight="9.29974574426651e-001"/><Con from="13" weight="9.27580966221869e-001"/><Con from="14" weight="1.67007466882672e-002"/><Con from="15" weight="9.75537883313109e-001"/><Con from="16" weight="6.99248659995944e-001"/><Con from="17" weight="6.38441675402026e-001"/><Con from="18" weight="9.87600288764657e-001"/><Con from="19" weight="3.20563966101318e-001"/><Con from="20" weight="5.25614242362251e-001"/><Con from="21" weight="4.61745956937303e-001"/></Neuron><Neuron id="34" width="2.43185135863709e-001"><Con from="0" weight="8.65676416209865e-001"/><Con from="1" weight="9.97764323260359e-001"/><Con from="2" weight="9.99740186917427e-001"/><Con from="3" weight="7.60272330150396e-001"/><Con from="4" weight="7.92823310327875e-001"/><Con from="5" weight="8.99986549439801e-001"/><Con from="6" weight="8.07409453324142e-001"/><Con from="7" weight="9.07091406885822e-001"/><Con from="8" weight="8.29962615304043e-001"/><Con from="9" weight="6.34202185312105e-001"/><Con from="10" weight="7.69343328652956e-001"/><Con from="11" weight="6.13820316340337e-001"/><Con from="12" weight="9.49617292659443e-001"/><Con from="13" weight="9.79769424008131e-001"/><Con from="14" weight="1.26642007001454e-002"/><Con from="15" weight="9.84719306613542e-001"/><Con from="16" weight="9.59949648503279e-001"/><Con from="17" weight="8.87016325792490e-001"/><Con from="18" weight="9.98279459307861e-001"/><Con from="19" weight="6.76208024911870e-001"/><Con from="20" weight="8.97427074303480e-001"/><Con from="21" weight="6.09864792843703e-001"/></Neuron><Neuron id="35" width="4.96217267091842e-001"><Con from="0" weight="7.31531133192078e-001"/><Con from="1" weight="8.84091559751315e-001"/><Con from="2" weight="9.56842895221305e-001"/><Con from="3" weight="4.91095868565067e-001"/><Con from="4" weight="6.85104178500167e-001"/><Con from="5" weight="5.37148475360355e-001"/><Con from="6" weight="4.58500375334910e-001"/><Con from="7" weight="8.86370540377758e-001"/><Con from="8" weight="7.69937998359240e-001"/><Con from="9" weight="6.48993632296180e-001"/><Con from="10" weight="3.99039145167720e-001"/><Con from="11" weight="4.11444455909378e-001"/><Con from="12" weight="9.48008600629278e-001"/><Con from="13" weight="9.39755548787241e-001"/><Con from="14" weight="1.45163965265436e-002"/><Con from="15" weight="9.84631619642879e-001"/><Con from="16" weight="8.71538800595908e-001"/><Con from="17" weight="8.14630286398633e-001"/><Con from="18" weight="9.90396523541031e-001"/><Con from="19" weight="2.82520284491101e-001"/><Con from="20" weight="7.81365060427002e-001"/><Con from="21" weight="2.52869504265913e-001"/></Neuron><Neuron id="36" width="4.28028416749282e-001"><Con from="0" weight="8.93722633410079e-001"/><Con from="1" weight="9.98099235721767e-001"/><Con from="2" weight="9.99609333538190e-001"/><Con from="3" weight="5.83460096235326e-001"/><Con from="4" weight="6.71477741483895e-001"/><Con from="5" weight="6.12853141900847e-001"/><Con from="6" weight="6.68501766742024e-001"/><Con from="7" weight="9.33348052782490e-001"/><Con from="8" weight="8.42279455830191e-001"/><Con from="9" weight="4.70088075907514e-001"/><Con from="10" weight="4.64513159573486e-001"/><Con from="11" weight="4.44666446775569e-001"/><Con from="12" weight="9.72135506055705e-001"/><Con from="13" weight="9.64536066297497e-001"/><Con from="14" weight="1.58029142700107e-002"/><Con from="15" weight="1.00000000000000e+000"/><Con from="16" weight="9.35502246304582e-001"/><Con from="17" weight="8.91586368136852e-001"/><Con from="18" weight="1.00000000000000e+000"/><Con from="19" weight="5.54354817852543e-001"/><Con from="20" weight="7.68304136592596e-001"/><Con from="21" weight="4.75776606446463e-001"/></Neuron><Neuron id="37" width="1.60855945850333e+000"><Con from="0" weight="3.38286759506396e-001"/><Con from="1" weight="9.28378224042394e-001"/><Con from="2" weight="4.67148100372302e-001"/><Con from="3" weight="6.48192371513411e-001"/><Con from="4" weight="7.09290148341307e-001"/><Con from="5" weight="2.68492827867912e-001"/><Con from="6" weight="6.23687654233168e-001"/><Con from="7" weight="0.00000000000000e+000"/><Con from="8" weight="2.70696962617601e-001"/><Con from="9" weight="7.40688039002360e-001"/><Con from="10" weight="4.31210211848431e-001"/><Con from="11" weight="6.39126353599208e-001"/><Con from="12" weight="5.89432694217703e-001"/><Con from="13" weight="0.00000000000000e+000"/><Con from="14" weight="3.40416873085396e-001"/><Con from="15" weight="1.00000000000000e+000"/><Con from="16" weight="0.00000000000000e+000"/><Con from="17" weight="0.00000000000000e+000"/><Con from="18" weight="6.43132709127193e-001"/><Con from="19" weight="0.00000000000000e+000"/><Con from="20" weight="4.79962809326836e-001"/><Con from="21" weight="0.00000000000000e+000"/></Neuron><Neuron id="38" width="3.88073603211138e-001"><Con from="0" weight="6.55633129653644e-001"/><Con from="1" weight="9.71236918525022e-001"/><Con from="2" weight="9.90046484472204e-001"/><Con from="3" weight="7.34760524958197e-001"/><Con from="4" weight="9.12787115705382e-001"/><Con from="5" weight="8.03030066697876e-001"/><Con from="6" weight="8.31403993931057e-001"/><Con from="7" weight="7.17741993074534e-001"/><Con from="8" weight="5.58070217895607e-001"/><Con from="9" weight="6.59140174833359e-001"/><Con from="10" weight="7.03095977285691e-001"/><Con from="11" weight="6.78717196889598e-001"/><Con from="12" weight="6.69869276730339e-001"/><Con from="13" weight="8.47176661715580e-001"/><Con from="14" weight="6.61228521980883e-002"/><Con from="15" weight="8.50560166823099e-001"/><Con from="16" weight="5.83759995118687e-001"/><Con from="17" weight="2.82449567923649e-001"/><Con from="18" weight="7.91528336561750e-001"/><Con from="19" weight="5.00262339412861e-001"/><Con from="20" weight="6.07273883534819e-001"/><Con from="21" weight="7.28444119688485e-001"/></Neuron><Neuron id="39" width="5.26801882853265e-001"><Con from="0" weight="6.80192893297338e-001"/><Con from="1" weight="9.81567664789004e-001"/><Con from="2" weight="9.81269894017109e-001"/><Con from="3" weight="7.68943083866460e-001"/><Con from="4" weight="9.08572906036610e-001"/><Con from="5" weight="7.98701724082714e-001"/><Con from="6" weight="7.53946602036768e-001"/><Con from="7" weight="4.11934532024587e-001"/><Con from="8" weight="5.67850503702585e-001"/><Con from="9" weight="7.93070395854857e-001"/><Con from="10" weight="7.24620352590937e-001"/><Con from="11" weight="6.01310272588218e-001"/><Con from="12" weight="5.96631913842534e-001"/><Con from="13" weight="7.54777945105346e-001"/><Con from="14" weight="1.08691953397964e-001"/><Con from="15" weight="9.01062268467889e-001"/><Con from="16" weight="5.59679395613379e-001"/><Con from="17" weight="2.12363769590776e-001"/><Con from="18" weight="8.81663503021195e-001"/><Con from="19" weight="3.19737035094156e-001"/><Con from="20" weight="3.52565005103489e-001"/><Con from="21" weight="5.79526886808502e-001"/></Neuron><Neuron id="40" width="2.43185135863709e-001"><Con from="0" weight="8.85434230063037e-001"/><Con from="1" weight="9.98849313858607e-001"/><Con from="2" weight="9.99451358626011e-001"/><Con from="3" weight="7.80495603927067e-001"/><Con from="4" weight="8.43608078963607e-001"/><Con from="5" weight="7.93621868530560e-001"/><Con from="6" weight="8.67638415481677e-001"/><Con from="7" weight="8.79467003512122e-001"/><Con from="8" weight="8.65877167973347e-001"/><Con from="9" weight="7.06423709259248e-001"/><Con from="10" weight="6.52254345519941e-001"/><Con from="11" weight="6.61841144899979e-001"/><Con from="12" weight="9.55547455999624e-001"/><Con from="13" weight="9.64834289420129e-001"/><Con from="14" weight="2.14537161764849e-002"/><Con from="15" weight="9.97950065349993e-001"/><Con from="16" weight="9.18854595294469e-001"/><Con from="17" weight="8.90448737577787e-001"/><Con from="18" weight="9.99999999999129e-001"/><Con from="19" weight="6.71130227217090e-001"/><Con from="20" weight="7.79100007331218e-001"/><Con from="21" weight="5.73914369565817e-001"/></Neuron><Neuron id="41" width="4.29507195491018e-001"><Con from="0" weight="8.07501810130848e-001"/><Con from="1" weight="9.91273953041215e-001"/><Con from="2" weight="9.88119214959397e-001"/><Con from="3" weight="7.58297349061780e-001"/><Con from="4" weight="8.71318681786393e-001"/><Con from="5" weight="8.90407250018870e-001"/><Con from="6" weight="6.70807616879240e-001"/><Con from="7" weight="8.78463803934928e-001"/><Con from="8" weight="8.04546978163737e-001"/><Con from="9" weight="8.15282239907031e-001"/><Con from="10" weight="7.69605326119406e-001"/><Con from="11" weight="6.71121761856220e-001"/><Con from="12" weight="8.18660097859377e-001"/><Con from="13" weight="8.75653825206845e-001"/><Con from="14" weight="4.20027276979018e-002"/><Con from="15" weight="7.31807075590261e-001"/><Con from="16" weight="6.08522250637883e-001"/><Con from="17" weight="4.94676080570061e-001"/><Con from="18" weight="7.85165309635134e-001"/><Con from="19" weight="6.20090480015396e-001"/><Con from="20" weight="6.79125118916436e-001"/><Con from="21" weight="6.97426087862224e-001"/></Neuron><Neuron id="42" width="6.92069495230223e-001"><Con from="0" weight="8.51106577926451e-001"/><Con from="1" weight="9.13578970755797e-001"/><Con from="2" weight="9.49970613920353e-001"/><Con from="3" weight="2.97824973976157e-001"/><Con from="4" weight="5.62261742420972e-001"/><Con from="5" weight="1.36066852692327e-001"/><Con from="6" weight="5.19414221205194e-001"/><Con from="7" weight="1.00000000000000e+000"/><Con from="8" weight="1.00000000000000e+000"/><Con from="9" weight="5.58988804366777e-001"/><Con from="10" weight="1.21544100375833e-001"/><Con from="11" weight="0.00000000000000e+000"/><Con from="12" weight="1.00000000000000e+000"/><Con from="13" weight="1.00000000000000e+000"/><Con from="14" weight="3.54354030174822e-002"/><Con from="15" weight="1.00000000000000e+000"/><Con from="16" weight="1.00000000000000e+000"/><Con from="17" weight="9.79256815899593e-001"/><Con from="18" weight="1.00000000000000e+000"/><Con from="19" weight="4.68204176293216e-001"/><Con from="20" weight="1.00000000000000e+000"/><Con from="21" weight="1.59293324201864e-001"/></Neuron><Neuron id="43" width="4.00442008192657e-001"><Con from="0" weight="8.14032293932573e-001"/><Con from="1" weight="9.98327995222287e-001"/><Con from="2" weight="9.98457124620014e-001"/><Con from="3" weight="4.83273335719561e-001"/><Con from="4" weight="7.92267464553789e-001"/><Con from="5" weight="5.86951180523456e-001"/><Con from="6" weight="7.70653894006067e-001"/><Con from="7" weight="8.70713563271257e-001"/><Con from="8" weight="7.63182959539155e-001"/><Con from="9" weight="7.81807918032091e-001"/><Con from="10" weight="4.59893303709089e-001"/><Con from="11" weight="4.03415749136368e-001"/><Con from="12" weight="9.19723806934653e-001"/><Con from="13" weight="9.59287918040216e-001"/><Con from="14" weight="3.74190106194883e-003"/><Con from="15" weight="9.86980039360318e-001"/><Con from="16" weight="9.33609325485819e-001"/><Con from="17" weight="7.72863917253004e-001"/><Con from="18" weight="9.87537700510706e-001"/><Con from="19" weight="4.38021552216166e-001"/><Con from="20" weight="7.94149017823833e-001"/><Con from="21" weight="4.98282356205372e-001"/></Neuron><Neuron id="44" width="4.60788289326208e-001"><Con from="0" weight="5.91918543855851e-001"/><Con from="1" weight="9.56070633513395e-001"/><Con from="2" weight="9.92023022031541e-001"/><Con from="3" weight="7.08479030218967e-001"/><Con from="4" weight="6.09873171105599e-001"/><Con from="5" weight="5.90351454366034e-001"/><Con from="6" weight="6.87694453434543e-001"/><Con from="7" weight="8.21880505271575e-001"/><Con from="8" weight="6.64083717028312e-001"/><Con from="9" weight="7.31649125286544e-001"/><Con from="10" weight="5.20775400481007e-001"/><Con from="11" weight="5.32765311355415e-001"/><Con from="12" weight="7.24983291676489e-001"/><Con from="13" weight="8.57563068998539e-001"/><Con from="14" weight="4.44324726122676e-002"/><Con from="15" weight="9.06005235914913e-001"/><Con from="16" weight="7.74834860136581e-001"/><Con from="17" weight="5.52069858045291e-001"/><Con from="18" weight="9.40110699889604e-001"/><Con from="19" weight="1.76806148813150e-001"/><Con from="20" weight="5.98269066799284e-001"/><Con from="21" weight="4.56631486085382e-001"/></Neuron><Neuron id="45" width="1.78922264414515e+000"><Con from="0" weight="6.73337601596199e-001"/><Con from="1" weight="-6.19614685011157e-001"/><Con from="2" weight="-1.04932563741012e+000"/><Con from="3" weight="9.91742760398942e-001"/><Con from="4" weight="1.00049616716653e+000"/><Con from="5" weight="9.81729234917434e-001"/><Con from="6" weight="9.74793837037308e-001"/><Con from="7" weight="7.58203783364257e-001"/><Con from="8" weight="6.85176918167963e-001"/><Con from="9" weight="9.98879930601909e-001"/><Con from="10" weight="9.37766516168958e-001"/><Con from="11" weight="9.41960475640281e-001"/><Con from="12" weight="6.82954417296695e-001"/><Con from="13" weight="8.26276424982787e-001"/><Con from="14" weight="7.74076935345218e-002"/><Con from="15" weight="5.64966125200088e-001"/><Con from="16" weight="6.22174969736795e-001"/><Con from="17" weight="4.23062605289607e-001"/><Con from="18" weight="3.47871678777872e-001"/><Con from="19" weight="6.99121982743565e-001"/><Con from="20" weight="6.46844840379654e-001"/><Con from="21" weight="8.99828507204513e-001"/></Neuron><Neuron id="46" width="3.45790979213797e-001"><Con from="0" weight="7.82656727975880e-001"/><Con from="1" weight="9.93525240152945e-001"/><Con from="2" weight="9.99384319714663e-001"/><Con from="3" weight="7.05680849060056e-001"/><Con from="4" weight="8.39079210974862e-001"/><Con from="5" weight="8.37138024914695e-001"/><Con from="6" weight="7.32786905273417e-001"/><Con from="7" weight="8.69806022679532e-001"/><Con from="8" weight="6.68937458693219e-001"/><Con from="9" weight="6.27715629527672e-001"/><Con from="10" weight="7.05576906643517e-001"/><Con from="11" weight="7.14332044448111e-001"/><Con from="12" weight="9.11175070064032e-001"/><Con from="13" weight="9.60073902864656e-001"/><Con from="14" weight="2.81899676078516e-002"/><Con from="15" weight="9.33268403642270e-001"/><Con from="16" weight="8.26042030865572e-001"/><Con from="17" weight="6.40879436967841e-001"/><Con from="18" weight="9.70342109033155e-001"/><Con from="19" weight="4.96866732021049e-001"/><Con from="20" weight="7.00212528477069e-001"/><Con from="21" weight="6.04751603685333e-001"/></Neuron><Neuron id="47" width="4.60788289326208e-001"><Con from="0" weight="8.12131136663751e-001"/><Con from="1" weight="9.66779362607507e-001"/><Con from="2" weight="9.86726412138275e-001"/><Con from="3" weight="5.81157263386597e-001"/><Con from="4" weight="4.67791246226350e-001"/><Con from="5" weight="4.22163269437918e-001"/><Con from="6" weight="6.45273446507912e-001"/><Con from="7" weight="8.71428282012587e-001"/><Con from="8" weight="7.95373524994985e-001"/><Con from="9" weight="5.43632596532568e-001"/><Con from="10" weight="5.18550852678878e-001"/><Con from="11" weight="6.28899901637301e-001"/><Con from="12" weight="6.70278462448696e-001"/><Con from="13" weight="8.75968619121764e-001"/><Con from="14" weight="4.71080780820270e-002"/><Con from="15" weight="9.94200149487239e-001"/><Con from="16" weight="7.34446136234791e-001"/><Con from="17" weight="5.46200246387982e-001"/><Con from="18" weight="9.64397573852742e-001"/><Con from="19" weight="2.78275380697874e-001"/><Con from="20" weight="6.70914668847052e-001"/><Con from="21" weight="3.93625358260232e-001"/></Neuron><Neuron id="48" width="4.28644170335955e-001"><Con from="0" weight="9.07310652129553e-001"/><Con from="1" weight="9.96850962179209e-001"/><Con from="2" weight="9.98418753937951e-001"/><Con from="3" weight="4.32112569846164e-001"/><Con from="4" weight="7.44005816420785e-001"/><Con from="5" weight="4.78090645120614e-001"/><Con from="6" weight="5.84549965676727e-001"/><Con from="7" weight="9.80836169297427e-001"/><Con from="8" weight="9.01661643165530e-001"/><Con from="9" weight="5.95720079451073e-001"/><Con from="10" weight="3.38819852655686e-001"/><Con from="11" weight="2.26015895735882e-001"/><Con from="12" weight="9.90399843766209e-001"/><Con from="13" weight="9.93033843515475e-001"/><Con from="14" weight="1.92604904119777e-002"/><Con from="15" weight="9.95795728454075e-001"/><Con from="16" weight="9.64554140848061e-001"/><Con from="17" weight="9.35125446842720e-001"/><Con from="18" weight="1.00000000000000e+000"/><Con from="19" weight="7.08495696713222e-001"/><Con from="20" weight="8.98483631137195e-001"/><Con from="21" weight="4.95276146863709e-001"/></Neuron><Neuron id="49" width="5.82285083080603e-001"><Con from="0" weight="7.64787104422229e-001"/><Con from="1" weight="9.75952148139001e-001"/><Con from="2" weight="9.97515190977355e-001"/><Con from="3" weight="9.04823728383933e-001"/><Con from="4" weight="8.98834667621603e-001"/><Con from="5" weight="9.10794793145965e-001"/><Con from="6" weight="8.78862069462019e-001"/><Con from="7" weight="8.70944384044887e-001"/><Con from="8" weight="8.02400089855555e-001"/><Con from="9" weight="8.59268345381513e-001"/><Con from="10" weight="8.09081319189125e-001"/><Con from="11" weight="8.08920534283322e-001"/><Con from="12" weight="8.98233499401611e-001"/><Con from="13" weight="9.62603058360848e-001"/><Con from="14" weight="3.60244308308659e-002"/><Con from="15" weight="6.43201090505709e-001"/><Con from="16" weight="8.66495499323367e-001"/><Con from="17" weight="7.89009401253540e-001"/><Con from="18" weight="9.78436210619561e-001"/><Con from="19" weight="8.21325789471651e-001"/><Con from="20" weight="8.09904742170643e-001"/><Con from="21" weight="8.00995136435416e-001"/></Neuron></NeuralLayer><NeuralLayer numberOfNeurons="2" activationFunction="identity"><Neuron id="50" bias="-9.58987447914731e-002"><Con from="22" weight="6.23914668084182e-001"/><Con from="23" weight="-2.98525055261725e-005"/><Con from="24" weight="6.33936399840792e-001"/><Con from="25" weight="1.69353415572739e-001"/><Con from="26" weight="-2.36673191598324e-004"/><Con from="27" weight="3.78418257914272e-012"/><Con from="28" weight="4.64153933379446e-003"/><Con from="29" weight="8.37352569458314e-003"/><Con from="30" weight="2.90065025730055e+000"/><Con from="31" weight="-4.87667255382228e-004"/><Con from="32" weight="7.67129557701448e-002"/><Con from="33" weight="-7.50643960132432e-002"/><Con from="34" weight="2.51690526681214e+003"/><Con from="35" weight="-1.05525402324441e-003"/><Con from="36" weight="8.57597846579066e-003"/><Con from="37" weight="2.26505046364066e-015"/><Con from="38" weight="1.17938950416451e-001"/><Con from="39" weight="5.95596512745701e-005"/><Con from="40" weight="-9.38061445799572e+003"/><Con from="41" weight="-2.90392685473841e-002"/><Con from="42" weight="-1.54115994190433e-007"/><Con from="43" weight="5.12793500865255e-002"/><Con from="44" weight="6.03114065523329e-003"/><Con from="45" weight="-3.66099963438436e-016"/><Con from="46" weight="-1.71793688548432e+000"/><Con from="47" weight="2.28852751369683e-003"/><Con from="48" weight="3.22078871110933e-002"/><Con from="49" weight="-2.06800662960903e-005"/></Neuron><Neuron id="51" bias="-7.56787212912032e-003"><Con from="22" weight="-3.05855762931143e-001"/><Con from="23" weight="2.12093155041127e-004"/><Con from="24" weight="2.04781501179618e-001"/><Con from="25" weight="3.59913533707361e-002"/><Con from="26" weight="-9.24839004025476e-004"/><Con from="27" weight="-8.02680981151298e-012"/><Con from="28" weight="4.28365662352059e-002"/><Con from="29" weight="1.99907940732300e-003"/><Con from="30" weight="8.41180197137322e+000"/><Con from="31" weight="-1.68262448510026e-004"/><Con from="32" weight="5.70935210851302e-003"/><Con from="33" weight="-4.06902352210673e-002"/><Con from="34" weight="8.00292469397799e+002"/><Con from="35" weight="-5.03278035691913e-004"/><Con from="36" weight="1.00971930006047e-002"/><Con from="37" weight="-6.46867959012624e-015"/><Con from="38" weight="1.43594284465661e-001"/><Con from="39" weight="-4.06774509413882e-005"/><Con from="40" weight="-4.35486526118846e+003"/><Con from="41" weight="-2.79831819028347e-002"/><Con from="42" weight="-8.46505459854055e-007"/><Con from="43" weight="1.18957645644744e-002"/><Con from="44" weight="5.33788416782980e-003"/><Con from="45" weight="-5.58941262442059e-018"/><Con from="46" weight="7.94311898833233e-001"/><Con from="47" weight="-6.81821296753864e-004"/><Con from="48" weight="2.07292000980028e-002"/><Con from="49" weight="-8.37778502265669e-006"/></Neuron></NeuralLayer><NeuralOutputs numberOfOutputs="2"><NeuralOutput outputNeuron="50"><DerivedField optype="categorical"><NormDiscrete field="E-cadherin" value="0"/></DerivedField></NeuralOutput><NeuralOutput outputNeuron="51"><DerivedField optype="categorical"><NormDiscrete field="E-cadherin" value="1"/></DerivedField></NeuralOutput></NeuralOutputs></NeuralNetwork></PMML>
