<?xml version="1.0" encoding="UTF-8"?>
<PMML version="3.0"><Header copyright="Copyright 1984-2017 TIBCO Software Inc. All rights reserved."><Application name="STATISTICA Automated Neural Networks (SANN)" version="2.0"/></Header><DataDictionary numberOfFields="23"><DataField name="IDCA" optype="categorical"><Value value="0"/><Value value="1"/></DataField><DataField name="wavelet-LLLglrlmShortRunEmphasis" optype="continuous"/><DataField name="wavelet-HLLglcmIdmn" optype="continuous"/><DataField name="wavelet-LHLglcmIdmn" optype="continuous"/><DataField name="originalglcmIdmn" optype="continuous"/><DataField name="wavelet-HLHglcmIdmn" optype="continuous"/><DataField name="originalglrlmShortRunEmphasis" optype="continuous"/><DataField name="wavelet-HHLglcmIdmn" optype="continuous"/><DataField name="wavelet-LLHglcmImc2" optype="continuous"/><DataField name="wavelet-LLHglcmIdmn" optype="continuous"/><DataField name="wavelet-HHHglcmIdn" optype="continuous"/><DataField name="wavelet-LHLglrlmShortRunEmphasis" optype="continuous"/><DataField name="originalglcmImc2" optype="continuous"/><DataField name="wavelet-HHLgldmDependenceEntropy" optype="continuous"/><DataField name="wavelet-LHHglszmZoneEntropy" optype="continuous"/><DataField name="wavelet-LLHglcmSumEntropy" optype="continuous"/><DataField name="wavelet-LLLglcmSumEntropy" optype="continuous"/><DataField name="wavelet-LLHglcmMCC" optype="continuous"/><DataField name="wavelet-HLLglrlmRunEntropy" optype="continuous"/><DataField name="wavelet-LHLglszmSmallAreaEmphasis" optype="continuous"/><DataField name="wavelet-HLLglcmImc2" optype="continuous"/><DataField name="wavelet-HLHglszmSmallAreaEmphasis" optype="continuous"/><DataField name="wavelet-HLLglszmSmallAreaEmphasis" optype="continuous"/></DataDictionary><NeuralNetwork modelName="Over2cc in Ove_RBF 22-9-2" functionName="classification"><MiningSchema><MiningField name="IDCA" usageType="predicted"/><MiningField name="wavelet-LLLglrlmShortRunEmphasis" lowValue="0.951459" highValue="0.994226"/><MiningField name="wavelet-HLLglcmIdmn" lowValue="0.952722" highValue="0.998206"/><MiningField name="wavelet-LHLglcmIdmn" lowValue="0.957705" highValue="0.996754"/><MiningField name="originalglcmIdmn" lowValue="0.943359" highValue="0.994506"/><MiningField name="wavelet-HLHglcmIdmn" lowValue="0.938441" highValue="0.997103"/><MiningField name="originalglrlmShortRunEmphasis" lowValue="0.910429" highValue="0.987686"/><MiningField name="wavelet-HHLglcmIdmn" lowValue="0.916094" highValue="0.997911"/><MiningField name="wavelet-LLHglcmImc2" lowValue="0.814424" highValue="0.999977"/><MiningField name="wavelet-LLHglcmIdmn" lowValue="0.883185" highValue="0.988362"/><MiningField name="wavelet-HHHglcmIdn" lowValue="0.866181" highValue="0.978344"/><MiningField name="wavelet-LHLglrlmShortRunEmphasis" lowValue="0.856875" highValue="0.981017"/><MiningField name="originalglcmImc2" lowValue="0.718192" highValue="0.999524"/><MiningField name="wavelet-HHLgldmDependenceEntropy" lowValue="4.521582" highValue="6.096989"/><MiningField name="wavelet-LHHglszmZoneEntropy" lowValue="4.231798" highValue="6.426798"/><MiningField name="wavelet-LLHglcmSumEntropy" lowValue="5.063844" highValue="7.085408"/><MiningField name="wavelet-LLLglcmSumEntropy" lowValue="5.256302" highValue="8.334624"/><MiningField name="wavelet-LLHglcmMCC" lowValue="0.617261" highValue="0.999731"/><MiningField name="wavelet-HLLglrlmRunEntropy" lowValue="3.211735" highValue="5.218720"/><MiningField name="wavelet-LHLglszmSmallAreaEmphasis" lowValue="0.433984" highValue="0.821654"/><MiningField name="wavelet-HLLglcmImc2" lowValue="0.586886" highValue="0.997333"/><MiningField name="wavelet-HLHglszmSmallAreaEmphasis" lowValue="0.487017" highValue="0.907413"/><MiningField name="wavelet-HLLglszmSmallAreaEmphasis" lowValue="0.464379" highValue="0.887391"/></MiningSchema><NeuralInputs numberOfInputs="22"><NeuralInput id="0"><DerivedField><NormContinuous field="wavelet-LLLglrlmShortRunEmphasis" shift="-2.22476140096223e+001" scale="2.33826341662426e+001"><LinearNorm orig="9.51458841268667e-001" norm="0.000000"/><LinearNorm orig="9.94225622500000e-001" norm="1.000000"/></NormContinuous></DerivedField></NeuralInput><NeuralInput id="1"><DerivedField><NormContinuous field="wavelet-HLLglcmIdmn" shift="-2.09462828700856e+001" scale="2.19857284803181e+001"><LinearNorm orig="9.52721802638333e-001" norm="0.000000"/><LinearNorm orig="9.98205853844333e-001" norm="1.000000"/></NormContinuous></DerivedField></NeuralInput><NeuralInput id="2"><DerivedField><NormContinuous field="wavelet-LHLglcmIdmn" shift="-2.45256192639272e+001" scale="2.56087382235451e+001"><LinearNorm orig="9.57705102447333e-001" norm="0.000000"/><LinearNorm orig="9.96754273526000e-001" norm="1.000000"/></NormContinuous></DerivedField></NeuralInput><NeuralInput id="3"><DerivedField><NormContinuous field="originalglcmIdmn" shift="-1.84443810202244e+001" scale="1.95518053404459e+001"><LinearNorm orig="9.43359485176000e-001" norm="0.000000"/><LinearNorm orig="9.94505657234667e-001" norm="1.000000"/></NormContinuous></DerivedField></NeuralInput><NeuralInput id="4"><DerivedField><NormContinuous field="wavelet-HLHglcmIdmn" shift="-1.59975838460759e+001" scale="1.70469738512845e+001"><LinearNorm orig="9.38441273251000e-001" norm="0.000000"/><LinearNorm orig="9.97102711270667e-001" norm="1.000000"/></NormContinuous></DerivedField></NeuralInput><NeuralInput id="5"><DerivedField><NormContinuous field="originalglrlmShortRunEmphasis" shift="-1.17843999726084e+001" scale="1.29437875890524e+001"><LinearNorm orig="9.10429029488667e-001" norm="0.000000"/><LinearNorm orig="9.87686168724000e-001" norm="1.000000"/></NormContinuous></DerivedField></NeuralInput><NeuralInput id="6"><DerivedField><NormContinuous field="wavelet-HHLglcmIdmn" shift="-1.11969287444794e+001" scale="1.22224610084140e+001"><LinearNorm orig="9.16094454036000e-001" norm="0.000000"/><LinearNorm orig="9.97911037399333e-001" norm="1.000000"/></NormContinuous></DerivedField></NeuralInput><NeuralInput id="7"><DerivedField><NormContinuous field="wavelet-LLHglcmImc2" shift="-4.38917559495539e+000" scale="5.38929740151092e+000"><LinearNorm orig="8.14424454238667e-001" norm="0.000000"/><LinearNorm orig="9.99977398435000e-001" norm="1.000000"/></NormContinuous></DerivedField></NeuralInput><NeuralInput id="8"><DerivedField><NormContinuous field="wavelet-LLHglcmIdmn" shift="-8.39713070919026e+000" scale="9.50778670989279e+000"><LinearNorm orig="8.83184590211000e-001" norm="0.000000"/><LinearNorm orig="9.88361539433000e-001" norm="1.000000"/></NormContinuous></DerivedField></NeuralInput><NeuralInput id="9"><DerivedField><NormContinuous field="wavelet-HHHglcmIdn" shift="-7.72253168314774e+000" scale="8.91560964032528e+000"><LinearNorm orig="8.66181001041000e-001" norm="0.000000"/><LinearNorm orig="9.78343830095000e-001" norm="1.000000"/></NormContinuous></DerivedField></NeuralInput><NeuralInput id="10"><DerivedField><NormContinuous field="wavelet-LHLglrlmShortRunEmphasis" shift="-6.90233749769271e+000" scale="8.05524745778473e+000"><LinearNorm orig="8.56874668825000e-001" norm="0.000000"/><LinearNorm orig="9.81017347897333e-001" norm="1.000000"/></NormContinuous></DerivedField></NeuralInput><NeuralInput id="11"><DerivedField><NormContinuous field="originalglcmImc2" shift="-2.55282274426968e+000" scale="3.55451338564430e+000"><LinearNorm orig="7.18191906262000e-001" norm="0.000000"/><LinearNorm orig="9.99524367700667e-001" norm="1.000000"/></NormContinuous></DerivedField></NeuralInput><NeuralInput id="12"><DerivedField><NormContinuous field="wavelet-HHLgldmDependenceEntropy" shift="-2.87010354373301e+000" scale="6.34756504152694e-001"><LinearNorm orig="4.52158193725667e+000" norm="0.000000"/><LinearNorm orig="6.09698918942000e+000" norm="1.000000"/></NormContinuous></DerivedField></NeuralInput><NeuralInput id="13"><DerivedField><NormContinuous field="wavelet-LHHglszmZoneEntropy" shift="-1.92792552450493e+000" scale="4.55580750611881e-001"><LinearNorm orig="4.23179759442333e+000" norm="0.000000"/><LinearNorm orig="6.42679814845667e+000" norm="1.000000"/></NormContinuous></DerivedField></NeuralInput><NeuralInput id="14"><DerivedField><NormContinuous field="wavelet-LLHglcmSumEntropy" shift="-2.50491422068523e+000" scale="4.94666555129291e-001"><LinearNorm orig="5.06384390598333e+000" norm="0.000000"/><LinearNorm orig="7.08540770412333e+000" norm="1.000000"/></NormContinuous></DerivedField></NeuralInput><NeuralInput id="15"><DerivedField><NormContinuous field="wavelet-LLLglcmSumEntropy" shift="-1.70752137828818e+000" scale="3.24852244690895e-001"><LinearNorm orig="5.25630161464000e+000" norm="0.000000"/><LinearNorm orig="8.33462419465334e+000" norm="1.000000"/></NormContinuous></DerivedField></NeuralInput><NeuralInput id="16"><DerivedField><NormContinuous field="wavelet-LLHglcmMCC" shift="-1.61387992288008e+000" scale="2.61458218474307e+000"><LinearNorm orig="6.17261118161667e-001" norm="0.000000"/><LinearNorm orig="9.99731405703334e-001" norm="1.000000"/></NormContinuous></DerivedField></NeuralInput><NeuralInput id="17"><DerivedField><NormContinuous field="wavelet-HLLglrlmRunEntropy" shift="-1.60027756221266e+000" scale="4.98259602190113e-001"><LinearNorm orig="3.21173451586000e+000" norm="0.000000"/><LinearNorm orig="5.21872042361667e+000" norm="1.000000"/></NormContinuous></DerivedField></NeuralInput><NeuralInput id="18"><DerivedField><NormContinuous field="wavelet-LHLglszmSmallAreaEmphasis" shift="-1.11946846882573e+000" scale="2.57951331344086e+000"><LinearNorm orig="4.33984373328333e-001" norm="0.000000"/><LinearNorm orig="8.21654401930000e-001" norm="1.000000"/></NormContinuous></DerivedField></NeuralInput><NeuralInput id="19"><DerivedField><NormContinuous field="wavelet-HLLglcmImc2" shift="-1.42987124866192e+000" scale="2.43636908857938e+000"><LinearNorm orig="5.86886139446000e-001" norm="0.000000"/><LinearNorm orig="9.97332982121667e-001" norm="1.000000"/></NormContinuous></DerivedField></NeuralInput><NeuralInput id="20"><DerivedField><NormContinuous field="wavelet-HLHglszmSmallAreaEmphasis" shift="-1.15847063074775e+000" scale="2.37870783174207e+000"><LinearNorm orig="4.87016780829000e-001" norm="0.000000"/><LinearNorm orig="9.07413092917333e-001" norm="1.000000"/></NormContinuous></DerivedField></NeuralInput><NeuralInput id="21"><DerivedField><NormContinuous field="wavelet-HLLglszmSmallAreaEmphasis" shift="-1.09779265560020e+000" scale="2.36399934781883e+000"><LinearNorm orig="4.64379424052333e-001" norm="0.000000"/><LinearNorm orig="8.87391385084667e-001" norm="1.000000"/></NormContinuous></DerivedField></NeuralInput></NeuralInputs><NeuralLayer numberOfNeurons="9" activationFunction="radialBasis"><Neuron id="22" width="4.24241591125462e-001"><Con from="0" weight="7.78207267029085e-001"/><Con from="1" weight="7.87138390828826e-001"/><Con from="2" weight="6.70422611855020e-001"/><Con from="3" weight="5.74822679357968e-001"/><Con from="4" weight="6.64817658969174e-001"/><Con from="5" weight="7.48969536153924e-001"/><Con from="6" weight="8.53749301969806e-001"/><Con from="7" weight="9.81660609597230e-001"/><Con from="8" weight="7.97233565490485e-001"/><Con from="9" weight="3.94328494187436e-001"/><Con from="10" weight="6.36728191446098e-001"/><Con from="11" weight="7.30848891804208e-001"/><Con from="12" weight="4.35612908853224e-001"/><Con from="13" weight="5.35581216830746e-001"/><Con from="14" weight="3.51619574762211e-001"/><Con from="15" weight="2.37371284226111e-001"/><Con from="16" weight="5.67266245321163e-001"/><Con from="17" weight="4.31486139062116e-001"/><Con from="18" weight="5.03114015755068e-001"/><Con from="19" weight="5.04997284315298e-001"/><Con from="20" weight="5.04430401180054e-001"/><Con from="21" weight="4.74322026712928e-001"/></Neuron><Neuron id="23" width="4.71806653654012e-001"><Con from="0" weight="-2.21110029362655e+001"/><Con from="1" weight="-2.07518357727073e+001"/><Con from="2" weight="-2.42678666251867e+001"/><Con from="3" weight="-1.82137172042047e+001"/><Con from="4" weight="-1.57954911244405e+001"/><Con from="5" weight="-1.16138092721151e+001"/><Con from="6" weight="-1.10229727462540e+001"/><Con from="7" weight="-4.27043867340534e+000"/><Con from="8" weight="-8.17003993623849e+000"/><Con from="9" weight="-7.47215997686719e+000"/><Con from="10" weight="-6.66299383920176e+000"/><Con from="11" weight="-2.35114014381105e+000"/><Con from="12" weight="-2.64538291264327e+000"/><Con from="13" weight="-1.71973070066606e+000"/><Con from="14" weight="-2.24677326210201e+000"/><Con from="15" weight="-1.50560623146477e+000"/><Con from="16" weight="-1.35012945841929e+000"/><Con from="17" weight="-1.34099736761329e+000"/><Con from="18" weight="-9.12989115155713e-001"/><Con from="19" weight="-1.16096748329477e+000"/><Con from="20" weight="-9.18440033008306e-001"/><Con from="21" weight="-8.70851128872723e-001"/></Neuron><Neuron id="24" width="1.39221463670365e+000"><Con from="0" weight="8.44402076165810e-001"/><Con from="1" weight="4.18056958746856e-001"/><Con from="2" weight="3.52529441677543e-001"/><Con from="3" weight="4.14185895926572e-001"/><Con from="4" weight="5.06847901518636e-001"/><Con from="5" weight="5.45923183278370e-001"/><Con from="6" weight="0.00000000000000e+000"/><Con from="7" weight="9.97826216171992e-001"/><Con from="8" weight="6.01440686477288e-001"/><Con from="9" weight="2.72183088739395e-001"/><Con from="10" weight="1.81356221684369e-001"/><Con from="11" weight="8.40400313581343e-001"/><Con from="12" weight="2.29430477984026e-001"/><Con from="13" weight="2.50687002972381e-001"/><Con from="14" weight="3.44093675895866e-001"/><Con from="15" weight="2.05599935556654e-001"/><Con from="16" weight="9.19326461685022e-001"/><Con from="17" weight="1.34021613857430e-001"/><Con from="18" weight="2.51069501248469e-001"/><Con from="19" weight="2.98498650229549e-001"/><Con from="20" weight="4.40045808724402e-001"/><Con from="21" weight="3.06676363248470e-002"/></Neuron><Neuron id="25" width="1.31445738073563e+000"><Con from="0" weight="7.12257870165573e-001"/><Con from="1" weight="9.45670028061603e-001"/><Con from="2" weight="8.55788006204058e-001"/><Con from="3" weight="9.56901987122880e-001"/><Con from="4" weight="9.59688640019241e-001"/><Con from="5" weight="6.61457037948781e-001"/><Con from="6" weight="9.74150176548669e-001"/><Con from="7" weight="1.92480994216272e-001"/><Con from="8" weight="9.84449262462624e-001"/><Con from="9" weight="8.89174553832369e-001"/><Con from="10" weight="6.25535168423045e-001"/><Con from="11" weight="1.14433167988159e-001"/><Con from="12" weight="7.06189768761237e-001"/><Con from="13" weight="8.27935406040784e-001"/><Con from="14" weight="5.89398442618011e-001"/><Con from="15" weight="6.04776798548493e-001"/><Con from="16" weight="3.48115975791092e-001"/><Con from="17" weight="4.66287760442078e-001"/><Con from="18" weight="5.28380334098869e-001"/><Con from="19" weight="1.44698875083313e-002"/><Con from="20" weight="4.01027684020000e-001"/><Con from="21" weight="3.75375717230676e-001"/></Neuron><Neuron id="26" width="4.71806653654012e-001"><Con from="0" weight="-2.21091558279467e+001"/><Con from="1" weight="-2.07484057090645e+001"/><Con from="2" weight="-2.42626083505384e+001"/><Con from="3" weight="-1.82072790247780e+001"/><Con from="4" weight="-1.57907420125957e+001"/><Con from="5" weight="-1.16080370488751e+001"/><Con from="6" weight="-1.10198803541768e+001"/><Con from="7" weight="-4.26960635740892e+000"/><Con from="8" weight="-8.15874474675989e+000"/><Con from="9" weight="-7.45181391787993e+000"/><Con from="10" weight="-6.64564682349144e+000"/><Con from="11" weight="-2.34063980347523e+000"/><Con from="12" weight="-2.82783172533683e+000"/><Con from="13" weight="-1.89042065595521e+000"/><Con from="14" weight="-2.46312245875594e+000"/><Con from="15" weight="-1.67619520825822e+000"/><Con from="16" weight="-1.31234152306195e+000"/><Con from="17" weight="-1.53999865228157e+000"/><Con from="18" weight="-7.99867667720902e-001"/><Con from="19" weight="-1.10446081664532e+000"/><Con from="20" weight="-8.13391807393484e-001"/><Con from="21" weight="-7.47911486775068e-001"/></Neuron><Neuron id="27" width="4.24241591125462e-001"><Con from="0" weight="8.23082952465416e-001"/><Con from="1" weight="6.58338222534187e-001"/><Con from="2" weight="5.71133440683994e-001"/><Con from="3" weight="5.76521867626120e-001"/><Con from="4" weight="6.57989561334848e-001"/><Con from="5" weight="7.35747375325884e-001"/><Con from="6" weight="8.12050280161733e-001"/><Con from="7" weight="9.62607153717019e-001"/><Con from="8" weight="6.60158616899071e-001"/><Con from="9" weight="5.23016576203791e-001"/><Con from="10" weight="6.08540731893454e-001"/><Con from="11" weight="8.25787714693898e-001"/><Con from="12" weight="5.04316758337346e-001"/><Con from="13" weight="6.01067584543533e-001"/><Con from="14" weight="5.50561136783327e-001"/><Con from="15" weight="3.86337801431271e-001"/><Con from="16" weight="6.73050252556337e-001"/><Con from="17" weight="5.42907289081952e-001"/><Con from="18" weight="5.47036245496854e-001"/><Con from="19" weight="5.83428748154731e-001"/><Con from="20" weight="4.96115579876893e-001"/><Con from="21" weight="4.35555432204141e-001"/></Neuron><Neuron id="28" width="8.63208578145966e-001"><Con from="0" weight="9.32581401522746e-001"/><Con from="1" weight="5.88498195622520e-001"/><Con from="2" weight="3.89242405309435e-001"/><Con from="3" weight="5.32012843413881e-001"/><Con from="4" weight="6.29952477462464e-001"/><Con from="5" weight="9.38359059251550e-001"/><Con from="6" weight="7.50158377062867e-001"/><Con from="7" weight="9.99644968119735e-001"/><Con from="8" weight="5.44623866760260e-001"/><Con from="9" weight="4.45448896817195e-001"/><Con from="10" weight="8.30964099211148e-001"/><Con from="11" weight="9.91120612788304e-001"/><Con from="12" weight="4.06077964554786e-001"/><Con from="13" weight="5.99277621280283e-001"/><Con from="14" weight="3.63287310923544e-001"/><Con from="15" weight="1.84633234172252e-001"/><Con from="16" weight="9.54195914291970e-001"/><Con from="17" weight="7.14117335456864e-001"/><Con from="18" weight="8.38791105505137e-001"/><Con from="19" weight="9.23527337010599e-001"/><Con from="20" weight="9.07853194937495e-001"/><Con from="21" weight="7.07395444489084e-001"/></Neuron><Neuron id="29" width="5.49153772345153e-001"><Con from="0" weight="8.31904591257860e-001"/><Con from="1" weight="5.62261610306159e-001"/><Con from="2" weight="7.88605172043980e-001"/><Con from="3" weight="6.78407886586967e-001"/><Con from="4" weight="5.68452027977123e-001"/><Con from="5" weight="7.33603902253726e-001"/><Con from="6" weight="8.50730891326775e-001"/><Con from="7" weight="9.98141681824774e-001"/><Con from="8" weight="5.03392152887480e-001"/><Con from="9" weight="5.21933281525460e-001"/><Con from="10" weight="4.55733267571116e-001"/><Con from="11" weight="9.37166744900545e-001"/><Con from="12" weight="5.57030669622066e-001"/><Con from="13" weight="6.17821044217106e-001"/><Con from="14" weight="6.47374144130787e-001"/><Con from="15" weight="4.02971859179865e-001"/><Con from="16" weight="9.09206972672658e-001"/><Con from="17" weight="6.74356929434617e-001"/><Con from="18" weight="5.82631391354600e-001"/><Con from="19" weight="7.79284974472926e-001"/><Con from="20" weight="6.02902342084320e-001"/><Con from="21" weight="5.98913542601462e-001"/></Neuron><Neuron id="30" width="1.28842746820049e+000"><Con from="0" weight="8.73326202868469e-001"/><Con from="1" weight="9.02855575140947e-001"/><Con from="2" weight="1.00000000000000e+000"/><Con from="3" weight="6.48542983079011e-001"/><Con from="4" weight="9.78327227478243e-001"/><Con from="5" weight="7.79740794385802e-001"/><Con from="6" weight="1.00000000000000e+000"/><Con from="7" weight="9.27798225697651e-001"/><Con from="8" weight="8.22675732750460e-001"/><Con from="9" weight="9.34396309751389e-001"/><Con from="10" weight="4.32580382145424e-001"/><Con from="11" weight="8.15124790871887e-001"/><Con from="12" weight="8.28430582782850e-001"/><Con from="13" weight="9.25293685161635e-001"/><Con from="14" weight="1.00000000000000e+000"/><Con from="15" weight="9.20923304918135e-001"/><Con from="16" weight="2.48666816955393e-001"/><Con from="17" weight="7.48617530031754e-001"/><Con from="18" weight="5.83465770365448e-001"/><Con from="19" weight="2.48619689449780e-001"/><Con from="20" weight="5.06158068756534e-001"/><Con from="21" weight="5.18724262334892e-001"/></Neuron></NeuralLayer><NeuralLayer numberOfNeurons="2" normalizationMethod="softmax"><Neuron id="31" bias="-9.46014669261424e-002"><Con from="22" weight="1.51107414684098e+000"/><Con from="23" weight="7.13857934086814e-003"/><Con from="24" weight="2.68791890109762e-013"/><Con from="25" weight="1.49685360262007e-013"/><Con from="26" weight="5.49201361317830e-003"/><Con from="27" weight="-2.47733557154047e+000"/><Con from="28" weight="1.61704089347158e-007"/><Con from="29" weight="8.64347475722483e-001"/><Con from="30" weight="4.58460533738007e-013"/></Neuron><Neuron id="32" bias="4.72036073865679e-001"><Con from="22" weight="-1.50160393565864e+000"/><Con from="23" weight="-3.87437341755116e-004"/><Con from="24" weight="1.73466472521154e-013"/><Con from="25" weight="3.92367845496867e-013"/><Con from="26" weight="5.78319046239744e-003"/><Con from="27" weight="2.53220972219181e+000"/><Con from="28" weight="-1.52341413018974e-007"/><Con from="29" weight="-8.64279420730594e-001"/><Con from="30" weight="1.09144884584120e-012"/></Neuron></NeuralLayer><NeuralOutputs numberOfOutputs="2"><NeuralOutput outputNeuron="31"><DerivedField optype="categorical"><NormDiscrete field="IDCA" value="0"/></DerivedField></NeuralOutput><NeuralOutput outputNeuron="32"><DerivedField optype="categorical"><NormDiscrete field="IDCA" value="1"/></DerivedField></NeuralOutput></NeuralOutputs></NeuralNetwork></PMML>
